README.md
setup.cfg
setup.py
el_config/__init__.py
el_config/__version__.py
el_config/config_base.py
el_config.egg-info/PKG-INFO
el_config.egg-info/SOURCES.txt
el_config.egg-info/dependency_links.txt
el_config.egg-info/requires.txt
el_config.egg-info/top_level.txt